random_filters/__init__.py
random_filters/random_checkbox.py
random_filters/random_combobox.py
random_filters/random_date.py
random_filters/random_date_partition.py
random_filters/random_store.py
random_filters/tests/__init__.py
random_filters/tests/test_random_filters.py
random_filters-1.6.0.dist-info/LICENSE
random_filters-1.6.0.dist-info/METADATA
random_filters-1.6.0.dist-info/WHEEL
random_filters-1.6.0.dist-info/RECORD
