Metadata-Version: 2.1
Name: random-filters
Version: 1.6.0
Summary: A package for generating random filters
Author: Renan
Author-email: renancavalcantercb@protonmail.com
Requires-Python: >=3.10,<4.0
Classifier: Programming Language :: Python :: 3
Classifier: Programming Language :: Python :: 3.10
Classifier: Programming Language :: Python :: 3.11
Requires-Dist: pandas (>=1.4.0,<2.0.0)
